mkdocs_pagetree_plugin/__init__.py
mkdocs_pagetree_plugin/plugin.py
mkdocs_pagetree_plugin/assets/mkdocs_pagetree_plugin.css
mkdocs_pagetree_plugin/assets/mkdocs_pagetree_plugin.js
mkdocs_pagetree_plugin/templates/nav_item.html.j2
mkdocs_pagetree_plugin/templates/nav_sub.html.j2
mkdocs_pagetree_plugin/templates/pagetree.html.j2
mkdocs_pagetree_plugin-0.0.17.dist-info/CC0-1.0.txt
mkdocs_pagetree_plugin-0.0.17.dist-info/METADATA
mkdocs_pagetree_plugin-0.0.17.dist-info/MIT.txt
mkdocs_pagetree_plugin-0.0.17.dist-info/WHEEL
mkdocs_pagetree_plugin-0.0.17.dist-info/entry_points.txt
mkdocs_pagetree_plugin-0.0.17.dist-info/top_level.txt
mkdocs_pagetree_plugin-0.0.17.dist-info/RECORD
