Metadata-Version: 2.2
Name: mkdocs-pagetree-plugin
Version: 0.0.17
Summary: MkDocs plugin that allows you to display the page tree
Author-email: Thomas Breitner <mail@thms.de>
License: MIT License
Project-URL: Homepage, https://tombreit.github.io/mkdocs-pagetree-plugin/
Project-URL: Documentation, https://github.com/tombreit/mkdocs-pagetree-plugin/blob/main/README.md
Project-URL: Repository, https://github.com/tombreit/mkdocs-pagetree-plugin
Project-URL: Issues, https://github.com/tombreit/mkdocs-pagetree-plugin/issues
Classifier: Framework :: MkDocs
Classifier: Topic :: Documentation
Classifier: License :: OSI Approved :: MIT License
Classifier: Programming Language :: Python :: 3
Classifier: Development Status :: 3 - Alpha
Requires-Python: >=3.9
License-File: LICENSES/CC0-1.0.txt
License-File: LICENSES/MIT.txt
Requires-Dist: mkdocs>=1.5
Provides-Extra: dev
Requires-Dist: pre-commit; extra == "dev"
Requires-Dist: reuse; extra == "dev"
Requires-Dist: ruff; extra == "dev"
Requires-Dist: pytest; extra == "dev"
Requires-Dist: beautifulsoup4; extra == "dev"
